jsock.py
jsock-0.1.0.dist-info/LICENSE
jsock-0.1.0.dist-info/METADATA
jsock-0.1.0.dist-info/WHEEL
jsock-0.1.0.dist-info/top_level.txt
jsock-0.1.0.dist-info/RECORD
