Metadata-Version: 2.1
Name: jsock
Version: 0.1.0
Summary: Key-value-based, HMAC-signed, non-blocking sockets for Python
Home-page: https://github.com/turicas/jsock
Author: Álvaro Justen
Author-email: alvarojusten@gmail.com
License: UNKNOWN
Platform: UNKNOWN
Classifier: Programming Language :: Python :: 2
Classifier: Programming Language :: Python :: 3
Requires-Dist: simplejson
